{
  "slug": "notarfachangestellter",
  "name": "Notarfachangestellte/r",
  "category": "Recht & Verwaltung",
  "categorySlug": "recht-verwaltung",
  "dauer": "1-2 Wochen",
  "beschreibung": "Im Praktikum als Notarfachangestellte/r erlebst du die besondere Welt der Beurkundungen und notariellen Beglaubigungen. Du lernst, wie Kaufverträge, Testamente und Gesellschaftsverträge vorbereitet und beurkundet werden. Dabei erlebst du die Präzision und Vertraulichkeit, die in einem Notariat gefordert werden, und die wichtige Rolle des Notars im Rechtssystem. Das Praktikum zeigt dir, ob dich die Verbindung von Recht und sorgfältiger Dokumentenarbeit anspricht.",
  "aufgaben": [
    "Urkundenentwürfe und Vertragstexte unter Anleitung vorbereiten",
    "Beurkundungstermine begleiten und den Ablauf beobachten",
    "Beglaubigungen und Unterschriftsbeglaubigungen kennenlernen",
    "Akten und Urkundenverzeichnisse pflegen",
    "Mandanten am Empfang und Telefon betreuen",
    "Grundbuch- und Handelsregisterauszüge anfordern und prüfen"
  ],
  "voraussetzungen": [
    "Höchste Sorgfalt und Genauigkeit bei Dokumenten",
    "Verschwiegenheit und Diskretion",
    "Interesse an rechtlichen Vorgängen und Vertragswerk",
    "Gute Deutschkenntnisse und Ausdrucksfähigkeit"
  ],
  "wasManLernt": [
    "Wie notarielle Beurkundungen ablaufen und warum sie nötig sind",
    "Grundlagen des Vertragsrechts und der Urkundenerstellung",
    "Umgang mit Grundbuch, Handelsregister und anderen Registern",
    "Die besondere Rolle und Verantwortung des Notars",
    "Professionelle Mandantenbetreuung in einem Notariat"
  ],
  "tipps": [
    "Kleide dich seriös – in einem Notariat wird ein professionelles Auftreten erwartet",
    "Frage nach, ob du bei einer Beurkundung dabei sein darfst",
    "Beachte die strenge Verschwiegenheitspflicht über alle Mandantenangelegenheiten",
    "Informiere dich vorab, was ein Notar macht und wie er sich vom Anwalt unterscheidet"
  ],
  "geeignetFuer": "Schüler ab Klasse 9",
  "relatedSlugs": ["rechtsanwaltsfachangestellter", "justizfachangestellter", "verwaltungsfachangestellter"]
}
